pheval_svanna/__init__.py
pheval_svanna/cli.py
pheval_svanna/post_process/__init__.py
pheval_svanna/post_process/post_process.py
pheval_svanna/post_process/post_process_results_format.py
pheval_svanna/prepare/__init__.py
pheval_svanna/prepare/prepare_commands.py
pheval_svanna/run/__init__.py
pheval_svanna/run/run.py
pheval_svanna/runner.py
pheval_svanna/tool_specific_configuration_parser.py
pheval_svanna-0.2.0.dist-info/METADATA
pheval_svanna-0.2.0.dist-info/WHEEL
pheval_svanna-0.2.0.dist-info/entry_points.txt
pheval_svanna-0.2.0.dist-info/RECORD
